awokado/__init__.py
awokado/auth.py
awokado/consts.py
awokado/custom_fields.py
awokado/db.py
awokado/db_helper.py
awokado/filter_parser.py
awokado/meta.py
awokado/middleware.py
awokado/request.py
awokado/resource.py
awokado/response.py
awokado/utils.py
awokado/version.py
awokado/documentation/__init__.py
awokado/documentation/generate.py
awokado/documentation/resources.py
awokado/documentation/routes.py
awokado/documentation/utils.py
awokado/exceptions/__init__.py
awokado/exceptions/auth.py
awokado/exceptions/bad_request.py
awokado/exceptions/base.py
awokado/exceptions/forbidden.py
awokado/exceptions/not_found.py
awokado-0.7.dist-info/LICENSE
awokado-0.7.dist-info/METADATA
awokado-0.7.dist-info/WHEEL
awokado-0.7.dist-info/top_level.txt
awokado-0.7.dist-info/RECORD
