Metadata-Version: 2.1
Name: awokado
Version: 0.7
Summary: Fast and flexible API framework based on Falcon and SQLAlchemy
Home-page: https://gitlab.com/5783354/awokado
Author: Dmitry Karnei
Author-email: 5783354@gmail.com
License: UNKNOWN
Keywords: api falcon rest sqlalchemy sqlalchemy-core wsgi
Platform: UNKNOWN
Classifier: Development Status :: 4 - Beta
Classifier: Environment :: Console
Classifier: Environment :: Web Environment
Classifier: Intended Audience :: Developers
Classifier: License :: OSI Approved :: MIT License
Classifier: Operating System :: OS Independent
Classifier: Programming Language :: Python :: 3.7
Classifier: Topic :: Internet :: WWW/HTTP :: WSGI :: Application
Classifier: Topic :: Software Development :: Libraries :: Python Modules
Classifier: Topic :: Software Development :: Libraries :: Application Frameworks
Requires-Python: >=3.7
Requires-Dist: sqlalchemy (<1.4.0,>=1.3.23)
Requires-Dist: dynaconf
Requires-Dist: psycopg2-binary
Requires-Dist: pyaml
Requires-Dist: clavis (==0.0.1b3)
Requires-Dist: marshmallow (<4.0.0,>=3.12.1)
Requires-Dist: falcon (<3.0.0,>=2.0.0)
Requires-Dist: apispec (<4.0.0,>=3.3.2)
Requires-Dist: bulky
Requires-Dist: boto3
Requires-Dist: cached-property
